doniclient/__init__.py
doniclient/osc/__init__.py
doniclient/osc/availability.py
doniclient/osc/cli.py
doniclient/osc/plugin.py
doniclient/osc/utils.py
doniclient/tests/__init__.py
doniclient/tests/test_doniclient.py
doniclient/v1/client.py
doniclient-0.4.1.dist-info/entry_points.txt
doniclient-0.4.1.dist-info/WHEEL
doniclient-0.4.1.dist-info/METADATA
doniclient-0.4.1.dist-info/RECORD
