Metadata-Version: 2.1
Name: doniclient
Version: 0.4.1
Summary: This is a plugin for the openstack commandline client, to enable support for the Doni hardware inventory project
Author: Michael Sherman
Author-email: shermanm@uchicago.edu
Requires-Python: >=3.6.2,<4.0.0
Classifier: Programming Language :: Python :: 3
Classifier: Programming Language :: Python :: 3.7
Classifier: Programming Language :: Python :: 3.8
Classifier: Programming Language :: Python :: 3.9
Requires-Dist: PyYAML (<=5.1.2)
Requires-Dist: keystoneauth1 (>=3.17.3)
Requires-Dist: osc-lib (>=1.14.1)
Requires-Dist: python-dateutil (<=2.8.0)
Requires-Dist: python-openstackclient[cli] (>=4.0.2)
